{
  "best_metric": null,
  "best_model_checkpoint": null,
  "epoch": 0.48,
  "eval_steps": 500,
  "global_step": 3,
  "is_hyper_param_search": false,
  "is_local_process_zero": true,
  "is_world_process_zero": true,
  "log_history": [
    {
      "epoch": 0.16,
      "grad_norm": 0.35325565934181213,
      "learning_rate": 2.5e-06,
      "loss": 0.7435,
      "step": 1
    },
    {
      "epoch": 0.32,
      "grad_norm": 0.3403419256210327,
      "learning_rate": 5e-06,
      "loss": 0.7343,
      "step": 2
    },
    {
      "epoch": 0.48,
      "grad_norm": 0.33344995975494385,
      "learning_rate": 4.8776412907378845e-06,
      "loss": 0.8445,
      "step": 3
    }
  ],
  "logging_steps": 1,
  "max_steps": 12,
  "num_input_tokens_seen": 0,
  "num_train_epochs": 2,
  "save_steps": 3,
  "stateful_callbacks": {
    "TrainerControl": {
      "args": {
        "should_epoch_stop": false,
        "should_evaluate": false,
        "should_log": false,
        "should_save": true,
        "should_training_stop": false
      },
      "attributes": {}
    }
  },
  "total_flos": 28742807191552.0,
  "train_batch_size": 2,
  "trial_name": null,
  "trial_params": null
}
